README.rst
setup.py
bin/mem-server
t4k/__init__.py
t4k/basic_manager_test.py
t4k/counter_sampler.py
t4k/crowdflower_results.py
t4k/date_iterator.py
t4k/dictionary.py
t4k/ensure_unicode.py
t4k/extrema.py
t4k/file_utils.py
t4k/grouper.py
t4k/html.py
t4k/id_generator.py
t4k/io_util.py
t4k/js.py
t4k/managed_process.py
t4k/mem_server.py
t4k/multiprocessing_utils.py
t4k/patterns.py
t4k/persistent_ordered_dict.py
t4k/remem_server.py
t4k/safe.py
t4k/sample.py
t4k/selenium_crawler.py
t4k/string_alignment.py
t4k/test_clean_exit.py
t4k/test_selenium_crawler.py
t4k/test_shared_progress_tracker.py
t4k/token_map.py
t4k/trace.py
t4k/track_progress.py
t4k/tsv.py
t4k/unigram_dictionary.py
t4k/vectorize.py
t4k.egg-info/PKG-INFO
t4k.egg-info/SOURCES.txt
t4k.egg-info/dependency_links.txt
t4k.egg-info/pbr.json
t4k.egg-info/requires.txt
t4k.egg-info/top_level.txt