Metadata-Version: 1.1
Name: t4k
Version: 0.6.4
Summary: my personal swiss army knife
Home-page: http://drgitlab.cs.mcgill.ca/enewe101/trix_for_kids
Author: edward newell
Author-email: edward.newell@gmail.com
License: MIT
Keywords: trix are for kids
Platform: UNKNOWN
Classifier: Development Status :: 2 - Pre-Alpha
Classifier: Intended Audience :: Science/Research
Classifier: Intended Audience :: Information Technology
Classifier: Programming Language :: Python :: 2.7
Classifier: Natural Language :: English
Classifier: Topic :: Utilities
